aitrados_broker/__init__.py
aitrados_broker/run.py
aitrados_broker/addition_custom_mcps/__init__.py
aitrados_broker/addition_custom_mcps/addition_broker_mcp_service.py
aitrados_broker/addition_custom_mcps/broker_mcp.py
aitrados_broker/addition_custom_mcps/parameter_validator/send_order_params.py
aitrados_broker/trade_middleware_service/__init__.py
aitrados_broker/trade_middleware_service/requests.py
aitrados_broker/trade_middleware_service/rpc_data_response.py
aitrados_broker/trade_middleware_service/subscriber.py
aitrados_broker/trade_middleware_service/trade_middleware_identity.py
aitrados_broker/trade_middleware_service/trade_middleware_rpc_service.py
aitrados_broker/utils/__init__.py
aitrados_broker/utils/broker_aitrados_map.py
aitrados_broker/utils/broker_gateway.py
aitrados_broker/utils/broker_map_op.py
aitrados_broker/utils/common_utils.py
aitrados_broker/utils/contant.py
aitrados_broker/utils/full_symbol_generator.py
aitrados_broker/utils/provider_setting.py
aitrados_mt5/__init__.py
aitrados_mt5/mt5_gateway.py
aitrados_mt5/Experts/aitrados_server.mq5
aitrados_mt5/Include/JAson.mqh
aitrados_mt5/Include/Zmq/AtomicCounter.mqh
aitrados_mt5/Include/Zmq/Context.mqh
aitrados_mt5/Include/Zmq/Errno.mqh
aitrados_mt5/Include/Zmq/Socket.mqh
aitrados_mt5/Include/Zmq/SocketOptions.mqh
aitrados_mt5/Include/Zmq/Z85.mqh
aitrados_mt5/Include/Zmq/Zmq.mqh
aitrados_mt5/Include/Zmq/ZmqMsg.mqh
aitrados_mt5/Libraries/libsodium.dll
aitrados_mt5/Libraries/libzmq.dll
ibapi/__init__.py
ibapi/account_summary_tags.py
ibapi/client.py
ibapi/client_utils.py
ibapi/comm.py
ibapi/commission_and_fees_report.py
ibapi/commission_report.py
ibapi/common.py
ibapi/connection.py
ibapi/const.py
ibapi/contract.py
ibapi/decoder.py
ibapi/decoder_utils.py
ibapi/enum_implem.py
ibapi/errors.py
ibapi/execution.py
ibapi/ibapi.pyproj
ibapi/ineligibility_reason.py
ibapi/message.py
ibapi/news.py
ibapi/object_implem.py
ibapi/order.py
ibapi/order_cancel.py
ibapi/order_condition.py
ibapi/order_state.py
aitrados_broker-0.0.19.dist-info/METADATA
aitrados_broker-0.0.19.dist-info/WHEEL
aitrados_broker-0.0.19.dist-info/RECORD
