Metadata-Version: 2.4
Name: aitrados-broker
Version: 0.0.19
Summary: AI aitrading broker for  finance-trading-ai-agents-mcp
Project-URL: Homepage, https://github.com/aitrados/aitrados-broker
Project-URL: Bug Tracker, https://github.com/aitrados//aitrados-brokep/issues
Project-URL: Repository, https://github.com/aitrados/aitrados-broker
Author-email: Alexander <support@aitrados.com>
License: MIT License
Classifier: Environment :: Console
Classifier: Environment :: Web Environment
Classifier: Intended Audience :: Developers
Classifier: Intended Audience :: Financial and Insurance Industry
Classifier: License :: OSI Approved :: MIT License
Classifier: Operating System :: OS Independent
Classifier: Programming Language :: Python :: 3
Classifier: Programming Language :: Python :: 3.10
Classifier: Programming Language :: Python :: 3.11
Classifier: Programming Language :: Python :: 3.12
Classifier: Programming Language :: Python :: 3.13
Classifier: Programming Language :: Python :: 3.14
Classifier: Topic :: Office/Business :: Financial
Classifier: Topic :: Office/Business :: Financial :: Investment
Classifier: Topic :: Scientific/Engineering :: Information Analysis
Classifier: Topic :: Software Development :: Libraries :: Python Modules
Requires-Python: >=3.10
Requires-Dist: aitrados-api
Requires-Dist: protobuf==5.29.3
Requires-Dist: requests>=2.32.3
Requires-Dist: tzlocal
Requires-Dist: websocket-client>=1.8.0
